hare/__init__.py
hare/column.py
hare/connection.py
hare/db.py
hare/exception.py
hare/table.py
hare/transaction.py
hare/util.py
hare-0.6.dist-info/DESCRIPTION.rst
hare-0.6.dist-info/METADATA
hare-0.6.dist-info/RECORD
hare-0.6.dist-info/WHEEL
hare-0.6.dist-info/metadata.json
hare-0.6.dist-info/top_level.txt
hare-0.6.dist-info/zip-safe
