Metadata-Version: 2.0
Name: hare
Version: 0.6
Summary: A python ORM based on pymysql with ActiveRecord
Home-page: https://github.com/bingtel/hare
Author: bingtel Wang
Author-email: bingtelwang@163.com
License: MIT
Keywords: python ORM orm ActiveRecord pymysql raw sql
Platform: UNKNOWN
Requires-Dist: PyMySQL
